ens_normalize/__init__.py
ens_normalize/normalization.py
ens_normalize/spec.pickle
ens_normalize-3.0.10.dist-info/METADATA
ens_normalize-3.0.10.dist-info/WHEEL
ens_normalize-3.0.10.dist-info/licenses/LICENSE
ens_normalize-3.0.10.dist-info/RECORD
