Metadata-Version: 2.4
Name: ens-normalize
Version: 3.0.10
Summary: Ethereum Name Service (ENS) Name Normalizer
License: MIT
License-File: LICENSE
Author: Jakub Karbowski
Author-email: jakub@namehash.io
Maintainer: NameHash Team
Maintainer-email: devops@namehash.io
Requires-Python: >=3.8,<4.0
Classifier: License :: OSI Approved :: MIT License
Classifier: Programming Language :: Python :: 3
Classifier: Programming Language :: Python :: 3.8
Classifier: Programming Language :: Python :: 3.9
Classifier: Programming Language :: Python :: 3.10
Classifier: Programming Language :: Python :: 3.11
Classifier: Programming Language :: Python :: 3.12
Classifier: Programming Language :: Python :: 3.13
Classifier: Programming Language :: Python :: 3.14
Requires-Dist: pyunormalize (>=17.0.0,<18.0.0)
Project-URL: Homepage, https://github.com/namehash/ens-normalize-python
Project-URL: Repository, https://github.com/namehash/ens-normalize-python
